MANIFEST.in
README.md
setup.py
pygclock/__init__.py
pygclock/clock.py
pygclock.egg-info/PKG-INFO
pygclock.egg-info/SOURCES.txt
pygclock.egg-info/dependency_links.txt
pygclock.egg-info/top_level.txt