Metadata-Version: 2.4
Name: pygclock
Version: 1.1.0
Summary: PyGClock, simple clock library like Clock on PyGame.
Author: azzammuhyala
License: MIT
Keywords: clock,simple clock,pygame clock,pygclock,simple pygame clock
Classifier: Programming Language :: Python :: 3
Classifier: Programming Language :: Python :: 3.5
Classifier: Topic :: Software Development :: Libraries :: Python Modules
Requires-Python: >=3.5
Dynamic: author
Dynamic: classifier
Dynamic: description
Dynamic: description-content-type
Dynamic: keywords
Dynamic: license
Dynamic: requires-python
Dynamic: summary
